<?xml version="1.0" encoding="UTF-8"?>
<!DOCTYPE mapper PUBLIC "-//mybatis.org//DTD Mapper 3.0//EN" "http://mybatis.org/dtd/mybatis-3-mapper.dtd">
<mapper namespace="com.heiheipp.common.mbg.mapper.TaskLogMapper">
  <resultMap id="BaseResultMap" type="com.heiheipp.common.mbg.model.TaskLog">
    <!--
      WARNING - @mbg.generated
      This element is automatically generated by MyBatis Generator, do not modify.
    -->
    <id column="parent_id" jdbcType="VARCHAR" property="parentId" />
    <id column="sub_id" jdbcType="VARCHAR" property="subId" />
    <result column="task_type" jdbcType="VARCHAR" property="taskType" />
    <result column="task_content" jdbcType="VARCHAR" property="taskContent" />
    <result column="status" jdbcType="VARCHAR" property="status" />
    <result column="total_nums" jdbcType="BIGINT" property="totalNums" />
    <result column="processed_nums" jdbcType="BIGINT" property="processedNums" />
    <result column="create_time" jdbcType="TIMESTAMP" property="createTime" />
    <result column="update_time" jdbcType="TIMESTAMP" property="updateTime" />
  </resultMap>
  <delete id="deleteByPrimaryKey" parameterType="map">
    <!--
      WARNING - @mbg.generated
      This element is automatically generated by MyBatis Generator, do not modify.
    -->
    delete from task_log
    where parent_id = #{parentId,jdbcType=VARCHAR}
      and sub_id = #{subId,jdbcType=VARCHAR}
  </delete>
  <insert id="insert" parameterType="com.heiheipp.common.mbg.model.TaskLog">
    <!--
      WARNING - @mbg.generated
      This element is automatically generated by MyBatis Generator, do not modify.
    -->
    insert into task_log (parent_id, sub_id, task_type, 
      task_content, `status`, total_nums, 
      processed_nums, create_time, update_time
      )
    values (#{parentId,jdbcType=VARCHAR}, #{subId,jdbcType=VARCHAR}, #{taskType,jdbcType=VARCHAR}, 
      #{taskContent,jdbcType=VARCHAR}, #{status,jdbcType=VARCHAR}, #{totalNums,jdbcType=BIGINT}, 
      #{processedNums,jdbcType=BIGINT}, #{createTime,jdbcType=TIMESTAMP}, #{updateTime,jdbcType=TIMESTAMP}
      )
  </insert>
  <update id="updateByPrimaryKey" parameterType="com.heiheipp.common.mbg.model.TaskLog">
    <!--
      WARNING - @mbg.generated
      This element is automatically generated by MyBatis Generator, do not modify.
    -->
    update task_log
    set task_type = #{taskType,jdbcType=VARCHAR},
      task_content = #{taskContent,jdbcType=VARCHAR},
      `status` = #{status,jdbcType=VARCHAR},
      total_nums = #{totalNums,jdbcType=BIGINT},
      processed_nums = #{processedNums,jdbcType=BIGINT},
      create_time = #{createTime,jdbcType=TIMESTAMP},
      update_time = #{updateTime,jdbcType=TIMESTAMP}
    where parent_id = #{parentId,jdbcType=VARCHAR}
      and sub_id = #{subId,jdbcType=VARCHAR}
  </update>
  <select id="selectByPrimaryKey" parameterType="map" resultMap="BaseResultMap">
    <!--
      WARNING - @mbg.generated
      This element is automatically generated by MyBatis Generator, do not modify.
    -->
    select parent_id, sub_id, task_type, task_content, `status`, total_nums, processed_nums, 
    create_time, update_time
    from task_log
    where parent_id = #{parentId,jdbcType=VARCHAR}
      and sub_id = #{subId,jdbcType=VARCHAR}
  </select>
  <select id="selectAll" resultMap="BaseResultMap">
    <!--
      WARNING - @mbg.generated
      This element is automatically generated by MyBatis Generator, do not modify.
    -->
    select parent_id, sub_id, task_type, task_content, `status`, total_nums, processed_nums, 
    create_time, update_time
    from task_log
  </select>
</mapper>